process_memory_writer-0.1.0.dist-info/METADATA
process_memory_writer-0.1.0.dist-info/WHEEL
process_memory_writer-0.1.0.dist-info/licenses/LICENSE
process_memory_writer/__init__.py
process_memory_writer/process_memory_writer.pyd
process_memory_writer-0.1.0.dist-info/RECORD
