Metadata-Version: 2.4
Name: process_memory_writer
Version: 0.1.0
Classifier: Programming Language :: Rust
Classifier: Programming Language :: Python :: Implementation :: CPython
Classifier: Programming Language :: Python :: Implementation :: PyPy
Classifier: Intended Audience :: Developers
Classifier: License :: OSI Approved :: MIT License
Classifier: Operating System :: Microsoft :: Windows
Classifier: Topic :: Software Development :: Libraries
License-File: LICENSE
Summary: A library for writing to process memory
Keywords: memory,process,automation,windows
Author-email: Austin Scriver <34779562+AScriver@users.noreply.github.com>
Requires-Python: >=3.11
